[
  {
    "_id": "67c0904b03368503b1006b18",
    "scores": {
      "tenMinutes": null,
      "halfTime": null,
      "fullTime": null,
      "extraTime": null,
      "penalties": null
    },
    "corners": {
      "halfTime": null,
      "fullTime": null
    },
    "bookings": {
      "halfTime": null,
      "fullTime": null
    },
    "uid": 1208287,
    "date": "2025-02-27T20:00:00.000Z",
    "status": "Not Started",
    "competition": 39,
    "competitionName": "Premier League",
    "teams": "West Ham v Leicester",
    "homeTeam": 48,
    "awayTeam": 46,
    "odds": []
  }
]
